{
  "$schema": "https://json-schema.org/draft/2020-12/schema",
  "$id": "https://skoji.dev/shelff/schemas/sidecar/v1",
  "title": "shelff Sidecar Metadata",
  "description": "Metadata for a single PDF file managed by shelff. Stored as a sidecar file named {filename}.pdf.meta.json alongside the PDF.",
  "type": "object",
  "required": ["schemaVersion", "metadata"],
  "additionalProperties": true,
  "properties": {
    "schemaVersion": {
      "type": "integer",
      "const": 1,
      "description": "Schema version. Must be 1 for this version of the specification."
    },
    "metadata": {
      "$ref": "#/$defs/DublinCoreMetadata"
    },
    "reading": {
      "$ref": "#/$defs/ReadingProgress"
    },
    "display": {
      "$ref": "#/$defs/DisplaySettings"
    },
    "category": {
      "type": "string",
      "description": "Category name assigned to this book. A book belongs to at most one category."
    },
    "tags": {
      "type": "array",
      "items": { "type": "string" },
      "description": "Tags assigned to this book. A book can have zero or more tags."
    }
  },
  "$defs": {
    "DublinCoreMetadata": {
      "type": "object",
      "description": "Metadata based on the Dublin Core Metadata Element Set. Field names use the 'dc:' prefix following Dublin Core convention.",
      "required": ["dc:title"],
      "additionalProperties": true,
      "properties": {
        "dc:title": {
          "type": "string",
          "description": "The title of the book."
        },
        "dc:creator": {
          "type": "array",
          "items": { "type": "string" },
          "description": "Authors or creators of the book."
        },
        "dc:date": {
          "type": "string",
          "description": "Publication date. Typically in ISO 8601 date format (e.g. \"2024-01-15\"), but not strictly enforced."
        },
        "dc:publisher": {
          "type": "string",
          "description": "Publisher of the book."
        },
        "dc:language": {
          "type": "string",
          "description": "Language of the book (e.g. \"ja\", \"en\")."
        },
        "dc:subject": {
          "type": "array",
          "items": { "type": "string" },
          "description": "Subject or topic keywords."
        },
        "dc:identifier": {
          "type": "string",
          "description": "An identifier for the book (e.g. ISBN, DOI)."
        }
      }
    },
    "ReadingProgress": {
      "type": "object",
      "description": "Reading progress and status for this book.",
      "required": ["lastReadPage", "lastReadAt", "totalPages"],
      "additionalProperties": false,
      "properties": {
        "lastReadPage": {
          "type": "integer",
          "minimum": 1,
          "description": "The last page the reader was on (1-indexed)."
        },
        "lastReadAt": {
          "type": "string",
          "format": "date-time",
          "description": "When the book was last read. ISO 8601 date-time in UTC."
        },
        "totalPages": {
          "type": "integer",
          "minimum": 1,
          "description": "Total number of pages in the PDF."
        },
        "status": {
          "type": "string",
          "enum": ["unread", "reading", "finished"],
          "description": "Reading status. 'unread' = not yet started, 'reading' = in progress, 'finished' = completed."
        },
        "finishedAt": {
          "type": "string",
          "format": "date-time",
          "description": "When the book was marked as finished. ISO 8601 date-time in UTC."
        }
      }
    },
    "DisplaySettings": {
      "type": "object",
      "description": "Display preferences for rendering this PDF.",
      "required": ["direction"],
      "additionalProperties": false,
      "properties": {
        "direction": {
          "type": "string",
          "enum": ["LTR", "RTL"],
          "description": "Reading direction. 'LTR' = left-to-right, 'RTL' = right-to-left."
        },
        "pageLayout": {
          "type": "string",
          "enum": ["single", "spread", "spread-with-cover"],
          "description": "Page layout mode. 'single' = one page at a time, 'spread' = two pages side by side, 'spread-with-cover' = spread with first page displayed alone."
        }
      }
    }
  }
}
